_my_cuda_kernels.cpython-310-x86_64-linux-gnu.so
cuda_ext_example-0.0.2.dist-info/WHEEL
cuda_ext_example-0.0.2.dist-info/METADATA
cuda_ext_example-0.0.2.dist-info/top_level.txt
cuda_ext_example-0.0.2.dist-info/RECORD
cuda_ext_example-0.0.2.dist-info/LICENSE.txt
cuda_ext_example/_add.py
cuda_ext_example/__init__.py
cuda_ext_example.libs/libcudart-d0da41ae.so.11.8.89
